pyocticons/__init__.py
pyocticons/data.json
pyocticons/octicons.py
pyocticons-0.1.1.dist-info/METADATA
pyocticons-0.1.1.dist-info/WHEEL
pyocticons-0.1.1.dist-info/RECORD
