Metadata-Version: 2.1
Name: pyocticons
Version: 0.1.1
Summary: python helper for github octicons
Keywords: octicons,icons
Author: Larry Ogrodnek
Author-email: ogrodnek@gmail.com
Requires-Python: >=3.10,<3.14
Classifier: Programming Language :: Python :: 3
Classifier: Programming Language :: Python :: 3.10
Classifier: Programming Language :: Python :: 3.11
Classifier: Programming Language :: Python :: 3.12
Classifier: Programming Language :: Python :: 3.13
